DELICENSE.txt
LICENSE
MANIFEST.in
README.rst
setup.py
juta_cms_icons/__init__.py
juta_cms_icons/apps.py
juta_cms_icons/fields.py
juta_cms_icons/forms.py
juta_cms_icons/json_reader.py
juta_cms_icons/models.py
juta_cms_icons/settings.py
juta_cms_icons/tests.py
juta_cms_icons/utils.py
juta_cms_icons/views.py
juta_cms_icons/widgets.py
juta_cms_icons/json_data/selection.json
juta_cms_icons/migrations/__init__.py
juta_cms_icons/static/juta_icon_lib/style.css
juta_cms_icons/static/juta_icon_lib/css/font-awesome.min.css
juta_cms_icons/static/juta_icon_lib/css/style-old-2.css
juta_cms_icons/static/juta_icon_lib/css/style-old.css
juta_cms_icons/static/juta_icon_lib/css/style.css
juta_cms_icons/static/juta_icon_lib/css/old-fonts/juta-portfolio-icon.svg
juta_cms_icons/static/juta_icon_lib/css/old-fonts/juta-portfolio-icon.ttf
juta_cms_icons/static/juta_icon_lib/css/old-fonts/juta-portfolio-icon.woff
juta_cms_icons/static/juta_icon_lib/fonts/juta-portfolio-icon.eot
juta_cms_icons/static/juta_icon_lib/fonts/juta-portfolio-icon.svg
juta_cms_icons/static/juta_icon_lib/fonts/juta-portfolio-icon.ttf
juta_cms_icons/static/juta_icon_lib/fonts/juta-portfolio-icon.woff
juta_cms_icons/static/juta_icon_lib/js/django_fontawesome.js
juta_cms_icons/static/juta_icon_lib/select2/select2-bootstrap.css
juta_cms_icons/static/juta_icon_lib/select2/select2-spinner.gif
juta_cms_icons/static/juta_icon_lib/select2/select2.css
juta_cms_icons/static/juta_icon_lib/select2/select2.min.js
juta_cms_icons/static/juta_icon_lib/select2/select2.png
juta_icons.egg-info/PKG-INFO
juta_icons.egg-info/SOURCES.txt
juta_icons.egg-info/dependency_links.txt
juta_icons.egg-info/top_level.txt